ctsimu/__init__.py
ctsimu/geometry.py
ctsimu/helpers.py
ctsimu/image.py
ctsimu/primitives.py
ctsimu/report.py
ctsimu/test.py
ctsimu/tiffy.py
ctsimu/toolbox.py
ctsimu/version.py
ctsimu/evaluation/__init__.py
ctsimu/evaluation/test2D_DW_1.py
ctsimu/evaluation/test2D_FB_1.py
ctsimu/evaluation/test2D_FB_2.py
ctsimu/evaluation/test2D_HS_1.py
ctsimu/evaluation/test2D_SW_1.py
ctsimu/evaluation/test2D_SW_2.py
ctsimu/evaluation/test2D_SW_3.py
ctsimu/evaluation/test2D_SW_4.py
ctsimu/evaluation/test2D_WE_1.py
ctsimu/evaluation/test2D_WE_2.py
ctsimu/evaluation/testTwin.py
ctsimu/evaluation/data/2D-SW-1_scenario07_Al_noFilter_050keV-mono_Ideal.txt
ctsimu/evaluation/data/2D-SW-1_scenario09_Al_noFilter_120kV-poly_Ideal.txt
ctsimu/evaluation/data/2D-SW-1_scenario11_Fe_noFilter_100kV-mono_Ideal.txt
ctsimu/evaluation/data/2D-SW-1_scenario13_Fe_noFilter_200kV-poly_Ideal.txt
ctsimu/evaluation/data/2D-SW-1_scenario15_Al_noFilter_050keV-mono_200mum-CsI.txt
ctsimu/evaluation/data/2D-SW-1_scenario17_Al_noFilter_120kV-poly_200mum-CsI.txt
ctsimu/evaluation/data/2D-SW-1_scenario19_Fe_noFilter_100keV-mono_200mum-CsI.txt
ctsimu/evaluation/data/2D-SW-1_scenario21_Fe_noFilter_200kV-poly_200mum-CsI.txt
ctsimu/evaluation/data/2D-SW-1_scenario23_Al_noFilter_050keV-mono_500mum-CsI.txt
ctsimu/evaluation/data/2D-SW-1_scenario25_Al_noFilter_120kV-poly_500mum-CsI.txt
ctsimu/evaluation/data/2D-SW-1_scenario27_Fe_noFilter_100keV-mono_500mum-CsI.txt
ctsimu/evaluation/data/2D-SW-1_scenario29_Fe_noFilter_200kV-poly_500mum-CsI.txt
ctsimu/evaluation/data/2D-SW-1_scenario31_Al_noFilter_050kV-mono_500mum-GOS.txt
ctsimu/evaluation/data/2D-SW-1_scenario33_Al_noFilter_120kV-poly_500mum-GOS.txt
ctsimu/evaluation/data/2D-SW-1_scenario35_Fe_noFilter_100keV-mono_500mum-GOS.txt
ctsimu/evaluation/data/2D-SW-1_scenario37_Fe_noFilter_200kV-poly_500mum-GOS.txt
ctsimu/evaluation/data/2D-SW-2_scenario01_Al_noFilter_200kV-poly_Ideal.txt
ctsimu/evaluation/data/2D-SW-2_scenario02_Al_CuFilter_200kV-poly_Ideal.txt
ctsimu-1.7.0.dist-info/licenses/LICENSE
ctsimu-1.7.0.dist-info/METADATA
ctsimu-1.7.0.dist-info/WHEEL
ctsimu-1.7.0.dist-info/top_level.txt
ctsimu-1.7.0.dist-info/zip-safe
ctsimu-1.7.0.dist-info/RECORD
