Metadata-Version: 2.4
Name: ctsimu
Version: 1.7.0
Summary: CTSimU Software Toolbox
Home-page: https://github.com/BAMresearch/ctsimu-toolbox/
Author: David Plotzki
Author-email: David Plotzki <davidplotzki@gmail.com>
Project-URL: Homepage, https://github.com/BAMresearch/ctsimu-toolbox/
Classifier: Programming Language :: Python :: 3
Classifier: License :: OSI Approved :: Apache Software License
Classifier: Operating System :: OS Independent
Classifier: Natural Language :: English
Classifier: Topic :: Multimedia :: Graphics :: Graphics Conversion
Requires-Python: >=3.9
License-File: LICENSE
Dynamic: author
Dynamic: home-page
Dynamic: license-file
Dynamic: requires-python
